anchorna/__init__.py
anchorna/cli.py
anchorna/core.py
anchorna/io.py
anchorna/util.py
anchorna/tests/conftest.py
anchorna/tests/pytest.ini
anchorna/tests/test_anchorna.py
anchorna/tests/data/anchors_complete.gff
anchorna/tests/data/anchors_complete_old.gff
anchorna/tests/data/anchors_subset.gff
anchorna/tests/data/anchors_subset_old.gff
anchorna/tests/data/pesti55.gff.zip
anchorna-2.0.0.dist-info/licenses/LICENSE
anchorna-2.0.0.dist-info/METADATA
anchorna-2.0.0.dist-info/WHEEL
anchorna-2.0.0.dist-info/entry_points.txt
anchorna-2.0.0.dist-info/top_level.txt
anchorna-2.0.0.dist-info/RECORD
