Metadata-Version: 2.4
Name: anchorna
Version: 2.0.0
Summary: Find anchors in RNA/DNA sequences
Author: Tom Eulenfeld
License-Expression: MIT
Project-URL: Homepage, https://github.com/rnajena/anchorna
Project-URL: Bug Tracker, https://github.com/rnajena/anchorna/issues
Keywords: bioinformatics,RNA,DNA,sequence,anchors
Classifier: Intended Audience :: Science/Research
Classifier: Operating System :: OS Independent
Classifier: Programming Language :: Python :: 3
Classifier: Topic :: Scientific/Engineering :: Bio-Informatics
License-File: LICENSE
Requires-Dist: rnajena-sugar>=0.5
Requires-Dist: tqdm
Dynamic: description
Dynamic: description-content-type
Dynamic: license-file
